{
  "publicPath": "/_nuxt/",
  "all": [
    "../server/index.spa.html",
    "065a76a.js",
    "0c441d6.js",
    "0feadf0.js",
    "129375c.js",
    "15ee29b.js",
    "3091eb0.js",
    "342dda5.js",
    "3490120.js",
    "41b0bee.js",
    "4477c8a.js",
    "6962bfa.js",
    "6a1b0a0.js",
    "7959260.js",
    "7973684.js",
    "7d646a6.js",
    "959d424.js",
    "9910e3c.js",
    "LICENSES",
    "be86803.js",
    "bfcd9cb.js",
    "c210149.js",
    "c5a4692.js",
    "c986758.js",
    "cec1a7f.js",
    "e43e3a7.js",
    "f5c6938.js",
    "fccb60e.js",
    "fonts/primeicons.3a0d4a5.ttf",
    "fonts/primeicons.dfbfef2.eot",
    "fonts/primeicons.e61f349.woff",
    "img/clipboard.b8e98e0.jpg",
    "img/clips1.551e4e4.jpg",
    "img/color.6441e63.png",
    "img/postit.6ca5453.jpg",
    "img/primeicons.c55d94a.svg",
    "img/relatorio.3733b0b.png",
    "img/sgae.03350ec.png"
  ],
  "initial": [
    "3091eb0.js",
    "065a76a.js",
    "c986758.js",
    "6a1b0a0.js"
  ],
  "async": [
    "0c441d6.js",
    "0feadf0.js",
    "129375c.js",
    "15ee29b.js",
    "342dda5.js",
    "3490120.js",
    "41b0bee.js",
    "4477c8a.js",
    "6962bfa.js",
    "7959260.js",
    "7973684.js",
    "7d646a6.js",
    "959d424.js",
    "9910e3c.js",
    "be86803.js",
    "bfcd9cb.js",
    "c210149.js",
    "c5a4692.js",
    "cec1a7f.js",
    "e43e3a7.js",
    "f5c6938.js",
    "fccb60e.js"
  ],
  "modules": {
    "12031190": [
      23,
      33,
      29,
      28,
      30,
      35
    ],
    "12038348": [
      23,
      33,
      29,
      28,
      30,
      35
    ],
    "12241538": [
      1
    ],
    "21193320": [
      10,
      8,
      13,
      37
    ],
    "21676025": [
      1
    ],
    "24980097": [
      1
    ],
    "25298670": [
      1
    ],
    "33594482": [
      1
    ],
    "35932707": [
      1
    ],
    "37579254": [
      8
    ],
    "44057554": [
      12,
      32
    ],
    "48738001": [
      8
    ],
    "49385148": [
      1
    ],
    "54489231": [
      1
    ],
    "64025317": [
      12,
      32
    ],
    "64642748": [
      1
    ],
    "66335742": [
      23,
      33,
      29,
      28,
      30,
      35
    ],
    "69590607": [
      23,
      33,
      29,
      28,
      30,
      35
    ],
    "70836496": [
      23,
      33,
      29,
      28,
      30,
      35
    ],
    "76213814": [
      23,
      33,
      29,
      28,
      30,
      35
    ],
    "82820260": [
      23,
      33,
      29,
      28,
      30,
      35
    ],
    "49698d8e": [
      23,
      33,
      29,
      28,
      30,
      35
    ],
    "b5ff0dd2": [
      1
    ],
    "fcd8355a": [
      1
    ],
    "7d27f18a": [
      12,
      32
    ],
    "34fdce6a": [
      1
    ],
    "370b78b9": [
      1
    ],
    "7eb310a2": [
      1
    ],
    "0836830c": [
      1
    ],
    "e1212bfc": [
      1
    ],
    "5bf5de08": [
      1
    ],
    "4c4de117": [
      23,
      33,
      29,
      28,
      30,
      35
    ],
    "15df5707": [
      23,
      33,
      29,
      28,
      30,
      35
    ],
    "1bfe647e": [
      23,
      33,
      29,
      28,
      30,
      35
    ],
    "12598cd0": [
      23,
      33,
      29,
      28,
      30,
      35
    ],
    "5b2986f1": [
      23,
      33,
      29,
      28,
      30,
      35
    ],
    "771b3ba0": [
      1
    ],
    "97672e34": [
      1
    ],
    "11de3a2e": [
      1
    ],
    "2de4b75c": [
      23,
      33,
      29,
      28,
      30,
      35
    ],
    "0c2b7908": [
      1
    ],
    "79988f5d": [
      1
    ],
    "3c46cfa6": [
      23,
      33,
      29,
      28,
      30,
      35
    ],
    "04049cbe": [
      1
    ],
    "4e437a7e": [
      1
    ],
    "14b7e3d8": [
      1
    ],
    "29b801fb": [
      1
    ],
    "3db3ca13": [
      1
    ],
    "624a2de3": [
      1
    ],
    "9517da82": [
      1
    ],
    "2d245b34": [
      1
    ],
    "06de9f1c": [
      1
    ],
    "9a95824a": [
      23,
      33,
      29,
      28,
      30,
      35
    ],
    "3d154c41": [
      1
    ],
    "f7a91202": [
      1
    ],
    "efbd0866": [
      1
    ],
    "5d81eec6": [
      23,
      33,
      29,
      28,
      30,
      35
    ],
    "9a89be0a": [
      1
    ],
    "29a3aa46": [
      1
    ],
    "1743d8fb": [
      1
    ],
    "feb8fdbc": [
      1
    ],
    "3b64aac9": [
      1
    ],
    "1a4dda94": [
      1
    ],
    "1ddedcf4": [
      1
    ],
    "92f93a60": [
      1
    ],
    "b1a1351e": [
      1
    ],
    "d0fb46ec": [
      1
    ],
    "7e98cd1a": [
      1
    ],
    "040d63b2": [
      23,
      33,
      29,
      28,
      30,
      35
    ],
    "2b328b04": [
      23,
      33,
      29,
      28,
      30,
      35
    ],
    "3dd91860": [
      23,
      33,
      29,
      28,
      30,
      35
    ],
    "c67d1b8e": [
      1
    ],
    "c7471e94": [
      1
    ],
    "215fbc76": [
      1
    ],
    "41f2ef37": [
      1
    ],
    "bf75a3b4": [
      1
    ],
    "6e44d372": [
      1
    ],
    "6513e9cc": [
      1
    ],
    "9cd23ada": [
      1
    ],
    "a28cf252": [
      1
    ],
    "61568cc7": [
      1
    ],
    "8855191c": [
      1
    ],
    "76f48d11": [
      23,
      33,
      29,
      28,
      30,
      35
    ],
    "5358dcbc": [
      23,
      33,
      29,
      28,
      30,
      35
    ],
    "813c0968": [
      23,
      33,
      29,
      28,
      30,
      35
    ],
    "ac8d83dc": [
      23,
      33,
      29,
      28,
      30,
      35
    ],
    "dc9356d6": [
      23,
      33,
      29,
      28,
      30,
      35
    ],
    "1686b61f": [
      23,
      33,
      29,
      28,
      30,
      35
    ],
    "6605a99b": [
      1
    ],
    "584bd9c9": [
      12,
      32
    ],
    "292546ac": [
      12,
      32
    ],
    "31689afa": [
      12,
      32
    ],
    "248c038c": [
      12,
      32
    ],
    "766c3b9c": [
      12,
      32
    ],
    "35b3e73a": [
      12,
      32
    ],
    "901e494c": [
      12,
      32
    ],
    "ec5206fc": [
      12,
      32
    ],
    "0c7eed26": [
      12,
      32
    ],
    "8a3d7cf2": [
      12,
      32
    ],
    "ff898996": [
      12,
      32
    ],
    "668490b2": [
      12,
      32
    ],
    "dc3875b4": [
      12,
      32
    ],
    "3395219a": [
      12,
      32
    ],
    "f4a28046": [
      12,
      32
    ],
    "ee1b6d5a": [
      12,
      32
    ],
    "df5935aa": [
      12,
      32
    ],
    "1d21e00a": [
      12,
      32
    ],
    "959f3c3c": [
      12,
      32
    ],
    "29cbd58b": [
      12,
      32
    ],
    "8cab56a2": [
      12,
      32
    ],
    "3f8f9329": [
      12,
      32
    ],
    "22859b9c": [
      12,
      32
    ],
    "6ab8cb42": [
      12,
      32
    ],
    "38ca81fc": [
      12,
      32
    ],
    "7df38a34": [
      12,
      32
    ],
    "2c2cc368": [
      12,
      32
    ],
    "dd4a6fc0": [
      12,
      32
    ],
    "3dbab425": [
      12,
      32
    ],
    "f7f42ffc": [
      12,
      32
    ],
    "3353a3a5": [
      12,
      32
    ],
    "f33cf8d8": [
      12,
      32
    ],
    "692b5fd7": [
      12,
      32
    ],
    "33fe2ab2": [
      12,
      32
    ],
    "ad6e1f56": [
      12,
      32
    ],
    "b01f6480": [
      12,
      32
    ],
    "bd8a2a6e": [
      12,
      32
    ],
    "693171d2": [
      12,
      32
    ],
    "4468a08d": [
      12,
      32
    ],
    "6db1bb36": [
      12,
      32
    ],
    "37ed5987": [
      12,
      32
    ],
    "4e2030ff": [
      12,
      32
    ],
    "25b1f0d5": [
      12,
      32
    ],
    "e17360ac": [
      12,
      32
    ],
    "0e87f2ae": [
      12,
      32
    ],
    "a01f0842": [
      12,
      32
    ],
    "05f31cbe": [
      12,
      32
    ],
    "4da34774": [
      12,
      32
    ],
    "4afe18b8": [
      12,
      32
    ],
    "15dc883e": [
      12,
      32
    ],
    "cf4c9662": [
      12,
      32
    ],
    "3f92bdea": [
      12,
      32
    ],
    "090269bc": [
      12,
      32
    ],
    "7d209e16": [
      12,
      32
    ],
    "21c1b206": [
      12,
      32
    ],
    "e50a2428": [
      12,
      32
    ],
    "100d7aaa": [
      12,
      32
    ],
    "651aa214": [
      12,
      32
    ],
    "46383dc2": [
      12,
      32
    ],
    "0203e840": [
      12,
      32
    ],
    "1de4d74e": [
      12,
      32
    ],
    "af1de1b0": [
      12,
      32
    ],
    "c7429f1c": [
      12,
      32
    ],
    "dd4d38d0": [
      12,
      32
    ],
    "706567cf": [
      1
    ],
    "1985cd93": [
      1
    ],
    "cee7b452": [
      1
    ],
    "4bf4b9f6": [
      1
    ],
    "055e2393": [
      1
    ],
    "2cbba8e4": [
      1
    ],
    "6e32ae1a": [
      23,
      33,
      29,
      28,
      30,
      35
    ],
    "5956cab4": [
      23,
      33,
      29,
      28,
      30,
      35
    ],
    "7a3163b5": [
      1
    ],
    "2db164dc": [
      1
    ],
    "c5502a92": [
      1
    ],
    "ac455a48": [
      1
    ],
    "0efe2d62": [
      23,
      33,
      29,
      28,
      30,
      35
    ],
    "3452ed92": [
      23,
      33,
      29,
      28,
      30,
      35
    ],
    "54927b82": [
      23,
      33,
      29,
      28,
      30,
      35
    ],
    "6eb10c8e": [
      23,
      33,
      29,
      28,
      30,
      35
    ],
    "3f165449": [
      23,
      33,
      29,
      28,
      30,
      35
    ],
    "40ac4ab0": [
      1
    ],
    "43baf242": [
      1
    ],
    "05d32e17": [
      1
    ],
    "094655c9": [
      1
    ],
    "22a23e7b": [
      1
    ],
    "f5ae6356": [
      23,
      33,
      29,
      28,
      30,
      35
    ],
    "215e399e": [
      23,
      33,
      29,
      28,
      30,
      35
    ],
    "1b644ed4": [
      1
    ],
    "43a48149": [
      1
    ],
    "3d7e992a": [
      1
    ],
    "57cdaee1": [
      1
    ],
    "695884e5": [
      1
    ],
    "e4ec6bdc": [
      1
    ],
    "2c570f0c": [
      1
    ],
    "3237575c": [
      1
    ],
    "7a98c314": [
      1
    ],
    "391039bf": [
      1
    ],
    "9701ba90": [
      1
    ],
    "42c9ae6c": [
      1
    ],
    "6927f519": [
      1
    ],
    "d1a4e78a": [
      1
    ],
    "7555aff1": [
      1
    ],
    "87a700a8": [
      23,
      33,
      29,
      28,
      30,
      35
    ],
    "0c536a57": [
      23,
      33,
      29,
      28,
      30,
      35
    ],
    "cd0ae396": [
      23,
      33,
      29,
      28,
      30,
      35
    ],
    "104a9359": [
      23,
      33,
      29,
      28,
      30,
      35
    ],
    "d669ca82": [
      23,
      33,
      29,
      28,
      30,
      35
    ],
    "56169bc1": [
      12,
      32
    ],
    "64cba91e": [
      23,
      33,
      29,
      28,
      30,
      35
    ],
    "0fd75b69": [
      1
    ],
    "fe1d406c": [
      1
    ],
    "229b03fb": [
      1
    ],
    "8624d400": [
      1
    ],
    "0268d572": [
      1
    ],
    "42731ca8": [
      1
    ],
    "140b1474": [
      1
    ],
    "1d9f3290": [
      1
    ],
    "80cd5330": [
      1
    ],
    "4c556f1e": [
      1
    ],
    "052bca84": [
      1
    ],
    "7987dc79": [
      1
    ],
    "4e0e1cd4": [
      1
    ],
    "d1d3781a": [
      1
    ],
    "9935c892": [
      1
    ],
    "6177d094": [
      1
    ],
    "327e6ae3": [
      1
    ],
    "aed06110": [
      1
    ],
    "7b9a630c": [
      1
    ],
    "42c89aa4": [
      1
    ],
    "aff490a6": [
      1
    ],
    "2df7d9cc": [
      1
    ],
    "29ae09a7": [
      1
    ],
    "259d9fda": [
      1
    ],
    "234ba7ee": [
      1
    ],
    "02886f17": [
      1
    ],
    "494c8d50": [
      23,
      33,
      29,
      28,
      30,
      35
    ],
    "3261fccf": [
      23,
      33,
      29,
      28,
      30,
      35
    ],
    "7260d536": [
      23,
      33,
      29,
      28,
      30,
      35
    ],
    "36ff5680": [
      12,
      32
    ],
    "26b27364": [
      23,
      33,
      29,
      28,
      30,
      35
    ],
    "0c5850b5": [
      1
    ],
    "779d3cca": [
      1
    ],
    "4403026b": [
      1
    ],
    "e908011a": [
      1
    ],
    "6c975f58": [
      1
    ],
    "1b352082": [
      1
    ],
    "5f8eb2a8": [
      1
    ],
    "6ed04732": [
      1
    ],
    "62334ce2": [
      1
    ],
    "6fdfe856": [
      1
    ],
    "5d370296": [
      1
    ],
    "5630d3a8": [
      1
    ],
    "e7db87a6": [
      1
    ],
    "3ebd7381": [
      1
    ],
    "628dc126": [
      1
    ],
    "81d197aa": [
      1
    ],
    "5248a850": [
      1
    ],
    "08368f1a": [
      1
    ],
    "643796ce": [
      1
    ],
    "e299c744": [
      1
    ],
    "2fd29987": [
      1
    ],
    "2ae7463c": [
      1
    ],
    "4f019f70": [
      1
    ],
    "af5ce968": [
      1
    ],
    "6888cdb8": [
      1
    ],
    "4fc97774": [
      1
    ],
    "7c6cb5fd": [
      1
    ],
    "51ef52fd": [
      1
    ],
    "0518c822": [
      23,
      33,
      29,
      28,
      30,
      35
    ],
    "d177b81c": [
      23,
      33,
      29,
      28,
      30,
      35
    ],
    "73652d7f": [
      23,
      33,
      29,
      28,
      30,
      35
    ],
    "2cd4b518": [
      23,
      33,
      29,
      28,
      30,
      35
    ],
    "05a35489": [
      23,
      33,
      29,
      28,
      30,
      35
    ],
    "7b995624": [
      23,
      33,
      29,
      28,
      30,
      35
    ],
    "dd8483fa": [
      23,
      33,
      29,
      28,
      30,
      35
    ],
    "4fe59026": [
      1
    ],
    "1d95defe": [
      1
    ],
    "c22bd5ca": [
      1
    ],
    "a3f6b742": [
      1
    ],
    "1bf73438": [
      1
    ],
    "2c59cb06": [
      1
    ],
    "2d4d4f16": [
      1
    ],
    "75cbd369": [
      1
    ],
    "542f71c3": [
      1
    ],
    "065efdb2": [
      1
    ],
    "a2fa1df6": [
      1
    ],
    "16dfde64": [
      1
    ],
    "22b6ea8f": [
      1
    ],
    "0b291874": [
      1
    ],
    "afaa08f8": [
      1
    ],
    "76fb9a3c": [
      1
    ],
    "a93584de": [
      1
    ],
    "20ef5fe8": [
      1
    ],
    "2fb97e9e": [
      1
    ],
    "3b423816": [
      1
    ],
    "5f8c6234": [
      1
    ],
    "82dda7cc": [
      1
    ],
    "3016bdca": [
      1
    ],
    "1f34fec8": [
      1
    ],
    "1022174c": [
      1
    ],
    "b5140b72": [
      1
    ],
    "2c9aaf36": [
      1
    ],
    "6389bc38": [
      1
    ],
    "5e9311ea": [
      1
    ],
    "1e7ae57b": [
      1
    ],
    "2503ad8c": [
      1
    ],
    "d4b18792": [
      1
    ],
    "054a96ef": [
      1
    ],
    "24cb1f68": [
      1
    ],
    "8f5af7ec": [
      1
    ],
    "c3e3e9f0": [
      1
    ],
    "79be3ed8": [
      1
    ],
    "65124fca": [
      1
    ],
    "46fc4919": [
      12,
      32
    ],
    "2be753b6": [
      12,
      32
    ],
    "09f10f36": [
      12,
      32
    ],
    "639c7eff": [
      12,
      32
    ],
    "bd9254bc": [
      12,
      32
    ],
    "d4498266": [
      12,
      32
    ],
    "3c2ccf05": [
      1
    ],
    "002230ba": [
      1
    ],
    "00fe492a": [
      1
    ],
    "d07ccdfc": [
      1
    ],
    "1a7dcdce": [
      23,
      33,
      29,
      28,
      30,
      35
    ],
    "1efc0f79": [
      23,
      33,
      29,
      28,
      30,
      35
    ],
    "1376d899": [
      23,
      33,
      29,
      28,
      30,
      35
    ],
    "f885eece": [
      23,
      33,
      29,
      28,
      30,
      35
    ],
    "81ccf50e": [
      23,
      33,
      29,
      28,
      30,
      35
    ],
    "28aeaca2": [
      1
    ],
    "4b47fd4b": [
      23,
      33,
      29,
      28,
      30,
      35
    ],
    "12e5a82f": [
      23,
      33,
      29,
      28,
      30,
      35
    ],
    "383acf65": [
      23,
      33,
      29,
      28,
      30,
      35
    ],
    "6d355303": [
      23,
      33,
      29,
      28,
      30,
      35
    ],
    "8e4af5ce": [
      23,
      33,
      29,
      28,
      30,
      35
    ],
    "ccf4324e": [
      23,
      33,
      29,
      28,
      30,
      35
    ],
    "722ef70e": [
      23,
      33,
      29,
      28,
      30,
      35
    ],
    "000dd239": [
      23,
      33,
      29,
      28,
      30,
      35
    ],
    "c44d197e": [
      23,
      33,
      29,
      28,
      30,
      35
    ],
    "1821f115": [
      23,
      33,
      29,
      28,
      30,
      35
    ],
    "44822b8e": [
      23,
      33,
      29,
      28,
      30,
      35
    ],
    "2daff8ce": [
      23,
      33,
      29,
      28,
      30,
      35
    ],
    "4eb06de7": [
      1
    ],
    "539aa503": [
      1
    ],
    "b28e329e": [
      1
    ],
    "e83308e8": [
      1
    ],
    "3c700aa6": [
      1
    ],
    "446af99e": [
      1
    ],
    "7ec5087c": [
      1
    ],
    "a38ec5bc": [
      23,
      33,
      29,
      28,
      30,
      35
    ],
    "58a6b37b": [
      1
    ],
    "72137f52": [
      23,
      33,
      29,
      28,
      30,
      35
    ],
    "4038cd7a": [
      23,
      33,
      29,
      28,
      30,
      35
    ],
    "68c9402c": [
      23,
      33,
      29,
      28,
      30,
      35
    ],
    "2578f69e": [
      23,
      33,
      29,
      28,
      30,
      35
    ],
    "193b25ab": [
      23,
      33,
      29,
      28,
      30,
      35
    ],
    "08d40fdc": [
      23,
      33,
      29,
      28,
      30,
      35
    ],
    "379582c8": [
      23,
      33,
      29,
      28,
      30,
      35
    ],
    "029b76ae": [
      23,
      33,
      29,
      28,
      30,
      35
    ],
    "ced674e6": [
      23,
      33,
      29,
      28,
      30,
      35
    ],
    "1ab609ba": [
      23,
      33,
      29,
      28,
      30,
      35
    ],
    "648cd9c1": [
      23,
      33,
      29,
      28,
      30,
      35
    ],
    "f015d6c0": [
      23,
      33,
      29,
      28,
      30,
      35
    ],
    "306a4e2c": [
      23,
      33,
      29,
      28,
      30,
      35
    ],
    "4cb73b22": [
      23,
      33,
      29,
      28,
      30,
      35
    ],
    "966617e0": [
      23,
      33,
      29,
      28,
      30,
      35
    ],
    "df1f40d8": [
      23,
      33,
      29,
      28,
      30,
      35
    ],
    "b7e48bcc": [
      23,
      33,
      29,
      28,
      30,
      35
    ],
    "2568f8ce": [
      23,
      33,
      29,
      28,
      30,
      35
    ],
    "3a704f5c": [
      23,
      33,
      29,
      28,
      30,
      35
    ],
    "108cd85b": [
      23,
      33,
      29,
      28,
      30,
      35
    ],
    "61daf699": [
      23,
      33,
      29,
      28,
      30,
      35
    ],
    "425c2c89": [
      23,
      33,
      29,
      28,
      30,
      35
    ],
    "64986cca": [
      23,
      33,
      29,
      28,
      30,
      35
    ],
    "71f0f732": [
      12,
      32
    ],
    "273bc0d9": [
      1
    ],
    "26945f94": [
      12,
      32
    ],
    "00b2e98b": [
      23,
      33,
      29,
      28,
      30,
      35
    ],
    "6fe398e8": [
      12,
      32
    ],
    "d4ade5be": [
      1
    ],
    "21a16fb8": [
      1
    ],
    "dbe44260": [
      1
    ],
    "4ba8cc28": [
      1
    ],
    "43ecbfac": [
      1
    ],
    "0673fc98": [
      1
    ],
    "f4bec70a": [
      1
    ],
    "b92460ba": [
      1
    ],
    "21c1321a": [
      1
    ],
    "cde32750": [
      1
    ],
    "88038cf2": [
      1
    ],
    "c3b653c4": [
      1
    ],
    "4eef08ce": [
      1
    ],
    "17028ac0": [
      1
    ],
    "caf5b4e0": [
      1
    ],
    "0b25d951": [
      1
    ],
    "23f83bc0": [
      1
    ],
    "746225ee": [
      1
    ],
    "0f6a8ab8": [
      1
    ],
    "13bf1a58": [
      1
    ],
    "536d9f3a": [
      1
    ],
    "ec94cb54": [
      1
    ],
    "6839eeda": [
      1
    ],
    "10e848dc": [
      1
    ],
    "6e9c605e": [
      12,
      32
    ],
    "5327491e": [
      12,
      32
    ],
    "5709e246": [
      12,
      32
    ],
    "5dc1327d": [
      12,
      32
    ],
    "3cd89d22": [
      12,
      32
    ],
    "4c9fe47f": [
      12,
      32
    ],
    "20ee034a": [
      12,
      32
    ],
    "2a17642f": [
      12,
      32
    ],
    "b4d65eb6": [
      12,
      32
    ],
    "06258efe": [
      12,
      32
    ],
    "7fe963d2": [
      23,
      33,
      29,
      28,
      30,
      35
    ],
    "3a79aebf": [
      23,
      33,
      29,
      28,
      30,
      35
    ],
    "3d2e6b28": [
      23,
      33,
      29,
      28,
      30,
      35
    ],
    "1855fdd0": [
      23,
      33,
      29,
      28,
      30,
      35
    ],
    "3d9b50b4": [
      23,
      33,
      29,
      28,
      30,
      35
    ],
    "7631d149": [
      23,
      33,
      29,
      28,
      30,
      35
    ],
    "3ab3fe6d": [
      23,
      33,
      29,
      28,
      30,
      35
    ],
    "610b4315": [
      23,
      33,
      29,
      28,
      30,
      35
    ],
    "2e5c8af4": [
      23,
      33,
      29,
      28,
      30,
      35
    ],
    "3ae4c7d8": [
      23,
      33,
      29,
      28,
      30,
      35
    ],
    "1a8548fe": [
      12,
      32
    ],
    "f9032bdc": [
      12,
      32
    ],
    "6e048ac7": [
      12,
      32
    ],
    "4b3ae0db": [
      12,
      32
    ],
    "1b32324c": [
      12,
      32
    ],
    "6c518574": [
      12,
      32
    ],
    "92388bf6": [
      12,
      32
    ],
    "e7b0bd1e": [
      12,
      32
    ],
    "575cb1ce": [
      12,
      32
    ],
    "4b21160e": [
      12,
      32
    ],
    "3514fc01": [
      12,
      32
    ],
    "52c067d1": [
      23,
      33,
      29,
      28,
      30,
      35
    ],
    "4cf5591e": [
      23,
      33,
      29,
      28,
      30,
      35
    ],
    "86757b9e": [
      23,
      33,
      29,
      28,
      30,
      35
    ],
    "39eb5dd1": [
      23,
      33,
      29,
      28,
      30,
      35
    ],
    "71c4595e": [
      23,
      33,
      29,
      28,
      30,
      35
    ],
    "be83621e": [
      23,
      33,
      29,
      28,
      30,
      35
    ],
    "85405f6a": [
      1
    ],
    "76ddf082": [
      1
    ],
    "5c810549": [
      1
    ],
    "21863b51": [
      23,
      33,
      29,
      28,
      30,
      35
    ],
    "c2a7521e": [
      23,
      33,
      29,
      28,
      30,
      35
    ],
    "f6faf076": [
      1
    ],
    "5ce2b831": [
      23,
      33,
      29,
      28,
      30,
      35
    ],
    "4bee585e": [
      23,
      33,
      29,
      28,
      30,
      35
    ],
    "1e6f497c": [
      1
    ],
    "13d6928f": [
      1
    ],
    "116266fd": [
      1
    ],
    "6783418d": [
      1
    ],
    "b120654e": [
      1
    ],
    "7df6d6db": [
      1
    ],
    "2ed60432": [
      1
    ],
    "56bed873": [
      1
    ],
    "319a6fa2": [
      1
    ],
    "777ba4ce": [
      1
    ],
    "08020e38": [
      1
    ],
    "68bd7d34": [
      1
    ],
    "04a334e6": [
      1
    ],
    "15fcea96": [
      1
    ],
    "412409ec": [
      1
    ],
    "4d4990a8": [
      1
    ],
    "059aeb7e": [
      1
    ],
    "02e4cd65": [
      1
    ],
    "725394eb": [
      1
    ],
    "7c3afdc6": [
      1
    ],
    "f6c71ab0": [
      1
    ],
    "40992cda": [
      1
    ],
    "a94373fa": [
      23,
      33,
      29,
      28,
      30,
      35
    ],
    "e7adacba": [
      23,
      33,
      29,
      28,
      30,
      35
    ],
    "632d0ce7": [
      23,
      33,
      29,
      28,
      30,
      35
    ],
    "2f3ac087": [
      23,
      33,
      29,
      28,
      30,
      35
    ],
    "711bdffb": [
      1
    ],
    "1bcf587a": [
      1
    ],
    "29d03b97": [
      1
    ],
    "cf5dcfc6": [
      23,
      33,
      29,
      28,
      30,
      35
    ],
    "791bfbbd": [
      23,
      33,
      29,
      28,
      30,
      35
    ],
    "6ac8588a": [
      23,
      33,
      29,
      28,
      30,
      35
    ],
    "9857514a": [
      23,
      33,
      29,
      28,
      30,
      35
    ],
    "14db9bd1": [
      23,
      33,
      29,
      28,
      30,
      35
    ],
    "144ae771": [
      23,
      33,
      29,
      28,
      30,
      35
    ],
    "374f1991": [
      23,
      33,
      29,
      28,
      30,
      35
    ],
    "9715959e": [
      23,
      33,
      29,
      28,
      30,
      35
    ],
    "7a8f7f31": [
      23,
      33,
      29,
      28,
      30,
      35
    ],
    "542ffad1": [
      23,
      33,
      29,
      28,
      30,
      35
    ],
    "c451f61e": [
      23,
      33,
      29,
      28,
      30,
      35
    ],
    "1afd2091": [
      23,
      33,
      29,
      28,
      30,
      35
    ],
    "23be500e": [
      23,
      33,
      29,
      28,
      30,
      35
    ],
    "8ba2e8ce": [
      23,
      33,
      29,
      28,
      30,
      35
    ],
    "b50969ba": [
      23,
      33,
      29,
      28,
      30,
      35
    ],
    "46958dcd": [
      23,
      33,
      29,
      28,
      30,
      35
    ],
    "9a3e3d26": [
      23,
      33,
      29,
      28,
      30,
      35
    ],
    "3dbe38f1": [
      23,
      33,
      29,
      28,
      30,
      35
    ],
    "76f9b6de": [
      23,
      33,
      29,
      28,
      30,
      35
    ],
    "468e8451": [
      23,
      33,
      29,
      28,
      30,
      35
    ],
    "2fc707f1": [
      23,
      33,
      29,
      28,
      30,
      35
    ],
    "27534ecc": [
      23,
      33,
      29,
      28,
      30,
      35
    ],
    "24058a5d": [
      23,
      33,
      29,
      28,
      30,
      35
    ],
    "23857e35": [
      23,
      33,
      29,
      28,
      30,
      35
    ],
    "0612541f": [
      23,
      33,
      29,
      28,
      30,
      35
    ],
    "3b68b6ba": [
      23,
      33,
      29,
      28,
      30,
      35
    ],
    "6cf4095c": [
      23,
      33,
      29,
      28,
      30,
      35
    ],
    "dbbe0eb8": [
      23,
      33,
      29,
      28,
      30,
      35
    ],
    "2012886a": [
      23,
      33,
      29,
      28,
      30,
      35
    ],
    "2cf612c6": [
      1
    ],
    "792ddbbc": [
      1
    ],
    "b3496724": [
      1
    ],
    "9b8bcfba": [
      1
    ],
    "5a167842": [
      1
    ],
    "021d6d76": [
      1
    ],
    "3782ccab": [
      1
    ],
    "5c8306ca": [
      1
    ],
    "005b2a16": [
      1
    ],
    "c30bb8c8": [
      1
    ],
    "80fe8b32": [
      1
    ],
    "86196fde": [
      1
    ],
    "179d9bf9": [
      1
    ],
    "22b27f90": [
      1
    ],
    "4fab745e": [
      1
    ],
    "27ce249e": [
      1
    ],
    "6be0750d": [
      1
    ],
    "0468898c": [
      23,
      33,
      29,
      28,
      30,
      35
    ],
    "69962ff5": [
      23,
      33,
      29,
      28,
      30,
      35
    ],
    "0ed36055": [
      23,
      33,
      29,
      28,
      30,
      35
    ],
    "6d8d58f7": [
      23,
      33,
      29,
      28,
      30,
      35
    ],
    "0a23ecdf": [
      23,
      33,
      29,
      28,
      30,
      35
    ],
    "265de214": [
      23,
      33,
      29,
      28,
      30,
      35
    ],
    "4a94ce2f": [
      23,
      33,
      29,
      28,
      30,
      35
    ],
    "4851e1aa": [
      23,
      33,
      29,
      28,
      30,
      35
    ],
    "2d65beb1": [
      23,
      33,
      29,
      28,
      30,
      35
    ],
    "4536a135": [
      23,
      33,
      29,
      28,
      30,
      35
    ],
    "02f3393e": [
      23,
      33,
      29,
      28,
      30,
      35
    ],
    "5a48b344": [
      23,
      33,
      29,
      28,
      30,
      35
    ],
    "eb8a29ec": [
      23,
      33,
      29,
      28,
      30,
      35
    ],
    "1e213fe7": [
      23,
      33,
      29,
      28,
      30,
      35
    ],
    "657344cf": [
      23,
      33,
      29,
      28,
      30,
      35
    ],
    "ea0d11b2": [
      23,
      33,
      29,
      28,
      30,
      35
    ],
    "22f9d8ee": [
      23,
      33,
      29,
      28,
      30,
      35
    ],
    "6b581994": [
      23,
      33,
      29,
      28,
      30,
      35
    ],
    "512f9c52": [
      23,
      33,
      29,
      28,
      30,
      35
    ],
    "c415a644": [
      23,
      33,
      29,
      28,
      30,
      35
    ],
    "4d801d20": [
      23,
      33,
      29,
      28,
      30,
      35
    ],
    "27c92a18": [
      23,
      33,
      29,
      28,
      30,
      35
    ],
    "ff88a27a": [
      23,
      33,
      29,
      28,
      30,
      35
    ],
    "c6cd54a8": [
      23,
      33,
      29,
      28,
      30,
      35
    ],
    "2f0137df": [
      23,
      33,
      29,
      28,
      30,
      35
    ],
    "efaf52ce": [
      23,
      33,
      29,
      28,
      30,
      35
    ],
    "dc83b4bc": [
      23,
      33,
      29,
      28,
      30,
      35
    ],
    "8f614184": [
      23,
      33,
      29,
      28,
      30,
      35
    ],
    "e63c211c": [
      23,
      33,
      29,
      28,
      30,
      35
    ],
    "08e814b8": [
      23,
      33,
      29,
      28,
      30,
      35
    ],
    "21d2d33c": [
      23,
      33,
      29,
      28,
      30,
      35
    ],
    "69e7862e": [
      23,
      33,
      29,
      28,
      30,
      35
    ],
    "58ff52f8": [
      23,
      33,
      29,
      28,
      30,
      35
    ],
    "4b22ff4a": [
      23,
      33,
      29,
      28,
      30,
      35
    ],
    "09d9bd95": [
      23,
      33,
      29,
      28,
      30,
      35
    ],
    "d0a7df6e": [
      23,
      33,
      29,
      28,
      30,
      35
    ],
    "44c7366a": [
      23,
      33,
      29,
      28,
      30,
      35
    ],
    "23967b60": [
      23,
      33,
      29,
      28,
      30,
      35
    ],
    "8c4bf5ac": [
      23,
      33,
      29,
      28,
      30,
      35
    ],
    "241c4a76": [
      23,
      33,
      29,
      28,
      30,
      35
    ],
    "2c0f2bcd": [
      23,
      33,
      29,
      28,
      30,
      35
    ],
    "751d7dea": [
      23,
      33,
      29,
      28,
      30,
      35
    ],
    "d0b61cd6": [
      23,
      33,
      29,
      28,
      30,
      35
    ],
    "60ac7ed7": [
      23,
      33,
      29,
      28,
      30,
      35
    ],
    "0b3c4150": [
      23,
      33,
      29,
      28,
      30,
      35
    ],
    "c9bf6080": [
      23,
      33,
      29,
      28,
      30,
      35
    ],
    "137cfd08": [
      23,
      33,
      29,
      28,
      30,
      35
    ],
    "3d278614": [
      23,
      33,
      29,
      28,
      30,
      35
    ],
    "57ba5018": [
      23,
      33,
      29,
      28,
      30,
      35
    ],
    "0c6f3c30": [
      23,
      33,
      29,
      28,
      30,
      35
    ],
    "167f6082": [
      23,
      33,
      29,
      28,
      30,
      35
    ],
    "08f70219": [
      23,
      33,
      29,
      28,
      30,
      35
    ],
    "28bcd6cb": [
      23,
      33,
      29,
      28,
      30,
      35
    ],
    "5a19d16a": [
      23,
      33,
      29,
      28,
      30,
      35
    ],
    "49af98f4": [
      23,
      33,
      29,
      28,
      30,
      35
    ],
    "03ff17da": [
      23,
      33,
      29,
      28,
      30,
      35
    ],
    "c124be72": [
      23,
      33,
      29,
      28,
      30,
      35
    ],
    "bd4c34ee": [
      23,
      33,
      29,
      28,
      30,
      35
    ],
    "4b411dd1": [
      23,
      33,
      29,
      28,
      30,
      35
    ],
    "1177cd8c": [
      23,
      33,
      29,
      28,
      30,
      35
    ],
    "5bd68b8c": [
      23,
      33,
      29,
      28,
      30,
      35
    ],
    "985aa356": [
      23,
      33,
      29,
      28,
      30,
      35
    ],
    "446b923c": [
      23,
      33,
      29,
      28,
      30,
      35
    ],
    "4395e5df": [
      23,
      33,
      29,
      28,
      30,
      35
    ],
    "51c0b280": [
      23,
      33,
      29,
      28,
      30,
      35
    ],
    "5a1dc8fc": [
      23,
      33,
      29,
      28,
      30,
      35
    ],
    "e88da63e": [
      23,
      33,
      29,
      28,
      30,
      35
    ],
    "dbc2af04": [
      23,
      33,
      29,
      28,
      30,
      35
    ],
    "378ca9eb": [
      23,
      33,
      29,
      28,
      30,
      35
    ],
    "d5d8e440": [
      12,
      32
    ],
    "0907f26e": [
      12,
      32
    ],
    "cbc4dbd8": [
      12,
      32
    ],
    "28e177ff": [
      12,
      32
    ],
    "75df768c": [
      23,
      33,
      29,
      28,
      30,
      35
    ],
    "acd9c606": [
      23,
      33,
      29,
      28,
      30,
      35
    ],
    "131e0155": [
      23,
      33,
      29,
      28,
      30,
      35
    ],
    "75fb16ff": [
      23,
      33,
      29,
      28,
      30,
      35
    ],
    "d0233a42": [
      23,
      33,
      29,
      28,
      30,
      35
    ],
    "5f28b5ac": [
      23,
      33,
      29,
      28,
      30,
      35
    ],
    "0e8d1ddf": [
      23,
      33,
      29,
      28,
      30,
      35
    ],
    "3cf1cf96": [
      23,
      33,
      29,
      28,
      30,
      35
    ],
    "128446e1": [
      23,
      33,
      29,
      28,
      30,
      35
    ],
    "4650b682": [
      23,
      33,
      29,
      28,
      30,
      35
    ],
    "4d898b8c": [
      23,
      33,
      29,
      28,
      30,
      35
    ],
    "89ea65ec": [
      23,
      33,
      29,
      28,
      30,
      35
    ],
    "2253c255": [
      23,
      33,
      29,
      28,
      30,
      35
    ],
    "135c57e8": [
      23,
      33,
      29,
      28,
      30,
      35
    ],
    "273c24df": [
      23,
      33,
      29,
      28,
      30,
      35
    ],
    "91d0cee8": [
      23,
      33,
      29,
      28,
      30,
      35
    ],
    "6e6994f9": [
      23,
      33,
      29,
      28,
      30,
      35
    ],
    "2ae33155": [
      23,
      33,
      29,
      28,
      30,
      35
    ],
    "7260bdfb": [
      23,
      33,
      29,
      28,
      30,
      35
    ],
    "2633bddf": [
      23,
      33,
      29,
      28,
      30,
      35
    ],
    "4572c27e": [
      23,
      33,
      29,
      28,
      30,
      35
    ],
    "1d436c46": [
      23,
      33,
      29,
      28,
      30,
      35
    ],
    "dcb95eba": [
      23,
      33,
      29,
      28,
      30,
      35
    ],
    "43cfe4ad": [
      23,
      33,
      29,
      28,
      30,
      35
    ],
    "3370f24c": [
      23,
      33,
      29,
      28,
      30,
      35
    ],
    "03ac9b5e": [
      23,
      33,
      29,
      28,
      30,
      35
    ],
    "058e4f95": [
      23,
      33,
      29,
      28,
      30,
      35
    ],
    "0220db53": [
      23,
      33,
      29,
      28,
      30,
      35
    ],
    "00dedc1f": [
      23,
      33,
      29,
      28,
      30,
      35
    ],
    "13ab63ac": [
      23,
      33,
      29,
      28,
      30,
      35
    ],
    "f14d4e58": [
      23,
      33,
      29,
      28,
      30,
      35
    ],
    "6c9f4e35": [
      23,
      33,
      29,
      28,
      30,
      35
    ],
    "7abf4054": [
      23,
      33,
      29,
      28,
      30,
      35
    ],
    "7187b0bf": [
      23,
      33,
      29,
      28,
      30,
      35
    ],
    "28013f20": [
      23,
      33,
      29,
      28,
      30,
      35
    ],
    "274e3e39": [
      23,
      33,
      29,
      28,
      30,
      35
    ],
    "b836fb7e": [
      23,
      33,
      29,
      28,
      30,
      35
    ],
    "0a1f2ebb": [
      23,
      33,
      29,
      28,
      30,
      35
    ],
    "0d44144b": [
      23,
      33,
      29,
      28,
      30,
      35
    ],
    "661ab4e4": [
      23,
      33,
      29,
      28,
      30,
      35
    ],
    "4c928fd2": [
      23,
      33,
      29,
      28,
      30,
      35
    ],
    "851db4da": [
      23,
      33,
      29,
      28,
      30,
      35
    ],
    "f6d92158": [
      23,
      33,
      29,
      28,
      30,
      35
    ],
    "6944a29d": [
      23,
      33,
      29,
      28,
      30,
      35
    ],
    "db4eca28": [
      23,
      33,
      29,
      28,
      30,
      35
    ],
    "47a06d89": [
      23,
      33,
      29,
      28,
      30,
      35
    ],
    "2ee79af5": [
      23,
      33,
      29,
      28,
      30,
      35
    ],
    "4b97968b": [
      23,
      33,
      29,
      28,
      30,
      35
    ],
    "2a38277f": [
      23,
      33,
      29,
      28,
      30,
      35
    ],
    "4074d1a4": [
      23,
      33,
      29,
      28,
      30,
      35
    ],
    "46fd880e": [
      23,
      33,
      29,
      28,
      30,
      35
    ],
    "6f6fe786": [
      23,
      33,
      29,
      28,
      30,
      35
    ],
    "815ba70a": [
      23,
      33,
      29,
      28,
      30,
      35
    ],
    "31a79e47": [
      23,
      33,
      29,
      28,
      30,
      35
    ],
    "7830f650": [
      23,
      33,
      29,
      28,
      30,
      35
    ],
    "20d307f4": [
      23,
      33,
      29,
      28,
      30,
      35
    ],
    "0a8bc5de": [
      23,
      33,
      29,
      28,
      30,
      35
    ],
    "d8d4cb14": [
      23,
      33,
      29,
      28,
      30,
      35
    ],
    "a32d4dca": [
      23,
      33,
      29,
      28,
      30,
      35
    ],
    "e992fd28": [
      23,
      33,
      29,
      28,
      30,
      35
    ],
    "bed10798": [
      23,
      33,
      29,
      28,
      30,
      35
    ],
    "0de21b16": [
      23,
      33,
      29,
      28,
      30,
      35
    ],
    "6cff7636": [
      23,
      33,
      29,
      28,
      30,
      35
    ],
    "7ddf53ff": [
      23,
      33,
      29,
      28,
      30,
      35
    ],
    "204fd4cc": [
      23,
      33,
      29,
      28,
      30,
      35
    ],
    "9b0d789c": [
      23,
      33,
      29,
      28,
      30,
      35
    ],
    "037657d6": [
      23,
      33,
      29,
      28,
      30,
      35
    ],
    "04cac534": [
      23,
      33,
      29,
      28,
      30,
      35
    ],
    "defa09c2": [
      23,
      33,
      29,
      28,
      30,
      35
    ],
    "279753a8": [
      8
    ],
    "388bb982": [
      8
    ],
    "538f5e7d": [
      8
    ],
    "36f1f649": [
      8
    ],
    "d852fdf6": [
      8
    ],
    "5b27b49e": [
      8
    ],
    "c5279ad6": [
      8
    ],
    "2d9eeb06": [
      8
    ],
    "1f4d5638": [
      8
    ],
    "ade11f66": [
      13
    ],
    "438f25a4": [
      8
    ],
    "90330d1a": [
      15,
      8,
      13,
      34
    ],
    "2b7ab8b3": [
      17,
      8,
      26,
      34
    ],
    "11c838ff": [
      26
    ],
    "8553e142": [
      16,
      37
    ],
    "58f3b216": [
      20,
      37
    ],
    "23bae7bc": [
      22,
      37
    ],
    "1e506a85": [
      3,
      25,
      31
    ],
    "21cde25e": [
      7,
      8,
      13,
      37
    ],
    "1b74bbe6": [
      24,
      37
    ],
    "b95012f2": [
      4,
      37
    ],
    "4a42c8ee": [
      14,
      31
    ],
    "4d0cad21": [
      10,
      8,
      13,
      37
    ],
    "5e3207a8": [
      11,
      34
    ],
    "e9a2cd6e": [
      5,
      37
    ],
    "504ad37c": [
      21,
      36
    ],
    "f0ef82ba": [
      19
    ],
    "1229ee40": [
      9
    ],
    "cbfca6bc": [
      8
    ],
    "98afd54e": [
      8
    ],
    "4a96ffb4": [
      8
    ],
    "e2205d9e": [
      8
    ],
    "4bd3bb76": [
      8
    ],
    "c397f260": [
      8
    ],
    "3f947b3a": [
      8
    ],
    "004d4bd2": [
      8
    ],
    "4f0b3aca": [
      8
    ],
    "3cbfbccf": [
      8
    ],
    "8617ab9e": [
      8
    ],
    "2a9c3e32": [
      8
    ],
    "286ddc4a": [
      8
    ],
    "4363f663": [
      8
    ],
    "456d5c08": [
      8
    ],
    "2d9fd3c4": [
      8
    ],
    "d9d6db0a": [
      8
    ],
    "ff07cd98": [
      8
    ],
    "35be7458": [
      8
    ],
    "7d62a6ef": [
      8
    ],
    "0e63436c": [
      8
    ],
    "30d8bcde": [
      8
    ],
    "9950e968": [
      8
    ],
    "2732b800": [
      8
    ],
    "331a9b3e": [
      8
    ],
    "9cb2c698": [
      8
    ],
    "57cb9a0d": [
      8
    ],
    "a98a4e74": [
      8
    ],
    "7f86a014": [
      8
    ],
    "939c6262": [
      8
    ],
    "c75f9f80": [
      8
    ],
    "61ea4ad1": [
      8
    ],
    "3b346432": [
      8
    ],
    "5c3cd98a": [
      15,
      8,
      13,
      34
    ],
    "8a1d3762": [
      15,
      8,
      13,
      34
    ],
    "6cdd5c7b": [
      17,
      8,
      26,
      34
    ],
    "27090e8f": [
      17,
      8,
      26,
      34
    ],
    "21912ec7": [
      26
    ],
    "6d6a55db": [
      26
    ],
    "c3980ed2": [
      16,
      37
    ],
    "23e2cb03": [
      16,
      37
    ],
    "0e6564bd": [
      20,
      37
    ],
    "3e90dfd1": [
      20,
      37
    ],
    "081da5ea": [
      22,
      37
    ],
    "1da51204": [
      22,
      37
    ],
    "b1c09580": [
      25
    ],
    "1fa15d50": [
      25
    ],
    "9c170b66": [
      3,
      25,
      31
    ],
    "532baa61": [
      3,
      25,
      31
    ],
    "3bc8fc26": [
      7,
      8,
      13,
      37
    ],
    "24d8cd3a": [
      7,
      8,
      13,
      37
    ],
    "71d09056": [
      24,
      37
    ],
    "449ba22e": [
      24,
      37
    ],
    "b9423b62": [
      4,
      37
    ],
    "7697e863": [
      4,
      37
    ],
    "4a49b4b6": [
      14,
      31
    ],
    "1d82baca": [
      14,
      31
    ],
    "f0282a2e": [
      10,
      8,
      13,
      37
    ],
    "8fd13406": [
      10,
      8,
      13,
      37
    ],
    "5c84ed38": [
      11,
      34
    ],
    "65a545d0": [
      11,
      34
    ],
    "36a1cd11": [
      5,
      37
    ],
    "4107b1b6": [
      5,
      37
    ],
    "5051bf44": [
      21,
      36
    ],
    "238ac558": [
      21,
      36
    ],
    "325fb002": [
      21,
      36
    ],
    "ef42684a": [
      19
    ],
    "1c468847": [
      19
    ],
    "384daca8": [
      9
    ],
    "1b0d4288": [
      9
    ],
    "1013f9ec": [
      26
    ],
    "620caf70": [
      26
    ],
    "20f6d197": [
      26
    ],
    "97439e1c": [
      26
    ],
    "563fb7a1": [
      26
    ],
    "45c3386d": [
      15,
      8,
      13,
      34
    ],
    "2137773e": [
      15,
      8,
      13,
      34
    ],
    "2da060d8": [
      15,
      8,
      13,
      34
    ],
    "d80bec80": [
      15,
      8,
      13,
      34
    ],
    "8dbd6ac4": [
      15,
      8,
      13,
      34
    ],
    "940a059a": [
      17,
      8,
      26,
      34
    ],
    "18eafa9c": [
      17,
      8,
      26,
      34
    ],
    "f38d5ee4": [
      17,
      8,
      26,
      34
    ],
    "10fca898": [
      17,
      8,
      26,
      34
    ],
    "e63e47d0": [
      17,
      8,
      26,
      34
    ],
    "461bf9d6": [
      16,
      37
    ],
    "92908d44": [
      16,
      37
    ],
    "19df7034": [
      16,
      37
    ],
    "093fc4c8": [
      16,
      37
    ],
    "a588922c": [
      16,
      37
    ],
    "051f4055": [
      27
    ],
    "676d832a": [
      27
    ],
    "4b4358a8": [
      27
    ],
    "0ebdc12c": [
      27
    ],
    "59a70936": [
      27
    ],
    "da7c09b2": [
      20,
      37
    ],
    "c30e76e8": [
      20,
      37
    ],
    "b23bbfcc": [
      20,
      37
    ],
    "22462fe4": [
      20,
      37
    ],
    "7f0eb024": [
      20,
      37
    ],
    "1aeb14fa": [
      22,
      37
    ],
    "31e3711a": [
      22,
      37
    ],
    "260a3ba7": [
      22,
      37
    ],
    "59d0d9f5": [
      22,
      37
    ],
    "1408929e": [
      22,
      37
    ],
    "68aa9203": [
      3,
      25,
      31
    ],
    "a3a83738": [
      3,
      25,
      31
    ],
    "4af2e084": [
      3,
      25,
      31
    ],
    "7e31ff34": [
      3,
      25,
      31
    ],
    "2068cb70": [
      3,
      25,
      31
    ],
    "142269fe": [
      7,
      8,
      13,
      37
    ],
    "44bf27b2": [
      7,
      8,
      13,
      37
    ],
    "58b1d323": [
      7,
      8,
      13,
      37
    ],
    "5062fea9": [
      7,
      8,
      13,
      37
    ],
    "28a34e2d": [
      7,
      8,
      13,
      37
    ],
    "3ee50d40": [
      24,
      37
    ],
    "ba98deca": [
      24,
      37
    ],
    "43c3e401": [
      24,
      37
    ],
    "559f671d": [
      24,
      37
    ],
    "1bf0740b": [
      24,
      37
    ],
    "cc34acc8": [
      4,
      37
    ],
    "1c50ad14": [
      4,
      37
    ],
    "9293cf76": [
      4,
      37
    ],
    "378c0fd4": [
      4,
      37
    ],
    "35fecdcf": [
      4,
      37
    ],
    "3b7341c9": [
      14,
      31
    ],
    "0ce947c1": [
      14,
      31
    ],
    "5a571cb8": [
      14,
      31
    ],
    "565ada7a": [
      14,
      31
    ],
    "4cc05b7c": [
      14,
      31
    ],
    "4e468524": [
      10,
      8,
      13,
      37
    ],
    "5e95e0c4": [
      10,
      8,
      13,
      37
    ],
    "4920dcbd": [
      10,
      8,
      13,
      37
    ],
    "214d6cc7": [
      10,
      8,
      13,
      37
    ],
    "c543b3a0": [
      11,
      34
    ],
    "50818a55": [
      11,
      34
    ],
    "b4e2c10e": [
      11,
      34
    ],
    "f47cc0da": [
      11,
      34
    ],
    "0f5c9b2f": [
      11,
      34
    ],
    "8e468c26": [
      5,
      37
    ],
    "fc9b95d8": [
      5,
      37
    ],
    "005b3114": [
      5,
      37
    ],
    "6acfa216": [
      5,
      37
    ],
    "590f109e": [
      5,
      37
    ],
    "de61b084": [
      21,
      36
    ],
    "7e2e16c5": [
      21,
      36
    ],
    "5db36463": [
      21,
      36
    ],
    "461761c7": [
      21,
      36
    ],
    "4607cc26": [
      21,
      36
    ],
    "922f60d4": [
      19
    ],
    "3a06d300": [
      19
    ],
    "062bb4d3": [
      19
    ],
    "6f46e83e": [
      19
    ],
    "6ff9b089": [
      19
    ],
    "4375597f": [
      9
    ],
    "0f330f07": [
      9
    ],
    "4739bc7c": [
      9
    ],
    "132a3809": [
      9
    ],
    "39eaa568": [
      9
    ],
    "2f0023e4": [
      2
    ],
    "b832a8cc": [
      2
    ],
    "1b8df29e": [
      2
    ]
  },
  "assetsMapping": {
    "085a35c4": [
      "065a76a.js"
    ],
    "bba68bf6": [
      "0c441d6.js"
    ],
    "361bba34": [
      "0feadf0.js"
    ],
    "7a3cef66": [
      "129375c.js"
    ],
    "2a130dde": [
      "15ee29b.js"
    ],
    "6fca0322": [
      "3091eb0.js"
    ],
    "5dadeaaf": [
      "342dda5.js"
    ],
    "146c4997": [
      "3490120.js"
    ],
    "53b86f5a": [
      "41b0bee.js"
    ],
    "a365f256": [
      "4477c8a.js"
    ],
    "bc32602e": [
      "6962bfa.js"
    ],
    "1a3ae26b": [
      "6a1b0a0.js"
    ],
    "20fd780c": [
      "7959260.js"
    ],
    "6197820c": [
      "7973684.js"
    ],
    "99c56ec4": [
      "7d646a6.js"
    ],
    "4258ad64": [
      "959d424.js"
    ],
    "51bd4364": [
      "9910e3c.js"
    ],
    "603e562b": [
      "be86803.js"
    ],
    "e4bc1350": [
      "bfcd9cb.js"
    ],
    "65f1f459": [
      "c210149.js"
    ],
    "189b73ab": [
      "c5a4692.js"
    ],
    "7ea24c87": [
      "c986758.js"
    ],
    "f0610dde": [
      "cec1a7f.js"
    ],
    "e1ee4b60": [
      "e43e3a7.js"
    ],
    "30a8dfb9": [
      "f5c6938.js"
    ],
    "525d6386": [
      "fccb60e.js"
    ]
  }
}